fontParts/__init__.py
fontParts/_version.py
fontParts/ui.py
fontParts/world.py
fontParts/base/__init__.py
fontParts/base/anchor.py
fontParts/base/bPoint.py
fontParts/base/base.py
fontParts/base/color.py
fontParts/base/compatibility.py
fontParts/base/component.py
fontParts/base/contour.py
fontParts/base/deprecated.py
fontParts/base/errors.py
fontParts/base/features.py
fontParts/base/font.py
fontParts/base/glyph.py
fontParts/base/groups.py
fontParts/base/guideline.py
fontParts/base/image.py
fontParts/base/info.py
fontParts/base/kerning.py
fontParts/base/layer.py
fontParts/base/lib.py
fontParts/base/normalizers.py
fontParts/base/point.py
fontParts/base/segment.py
fontParts/fontshell/__init__.py
fontParts/fontshell/anchor.py
fontParts/fontshell/bPoint.py
fontParts/fontshell/base.py
fontParts/fontshell/component.py
fontParts/fontshell/contour.py
fontParts/fontshell/features.py
fontParts/fontshell/font.py
fontParts/fontshell/glyph.py
fontParts/fontshell/groups.py
fontParts/fontshell/guideline.py
fontParts/fontshell/image.py
fontParts/fontshell/info.py
fontParts/fontshell/kerning.py
fontParts/fontshell/layer.py
fontParts/fontshell/lib.py
fontParts/fontshell/point.py
fontParts/fontshell/segment.py
fontParts/fontshell/test.py
fontParts/test/__init__.py
fontParts/test/legacyPointPen.py
fontParts/test/test_anchor.py
fontParts/test/test_bPoint.py
fontParts/test/test_color.py
fontParts/test/test_component.py
fontParts/test/test_contour.py
fontParts/test/test_deprecated.py
fontParts/test/test_features.py
fontParts/test/test_font.py
fontParts/test/test_fuzzyNumber.py
fontParts/test/test_glyph.py
fontParts/test/test_groups.py
fontParts/test/test_guideline.py
fontParts/test/test_image.py
fontParts/test/test_info.py
fontParts/test/test_kerning.py
fontParts/test/test_layer.py
fontParts/test/test_lib.py
fontParts/test/test_normalizers.py
fontParts/test/test_point.py
fontParts/test/test_segment.py
fontParts/test/test_world.py
fontparts-0.14.0.dist-info/licenses/LICENSE
fontparts-0.14.0.dist-info/METADATA
fontparts-0.14.0.dist-info/WHEEL
fontparts-0.14.0.dist-info/top_level.txt
fontparts-0.14.0.dist-info/zip-safe
fontparts-0.14.0.dist-info/RECORD
