Metadata-Version: 2.4
Name: fontParts
Version: 0.14.0
Summary: An API for interacting with the parts of fonts during the font development process.
Home-page: http://github.com/robotools/fontParts
Author: Just van Rossum, Tal Leming, Erik van Blokland, Ben Kiel, others
Author-email: info@robofab.com
Maintainer: Just van Rossum, Tal Leming, Erik van Blokland, Ben Kiel
Maintainer-email: info@robofab.com
License: OpenSource, MIT
Platform: Any
Classifier: Development Status :: 4 - Beta
Classifier: Environment :: Console
Classifier: Environment :: Other Environment
Classifier: Intended Audience :: Developers
Classifier: Intended Audience :: End Users/Desktop
Classifier: License :: OSI Approved :: MIT License
Classifier: Natural Language :: English
Classifier: Operating System :: OS Independent
Classifier: Programming Language :: Python
Classifier: Topic :: Multimedia :: Graphics
Classifier: Topic :: Multimedia :: Graphics :: Graphics Conversion
Classifier: Topic :: Software Development :: Libraries
Requires-Python: >=3.8
License-File: LICENSE
Requires-Dist: FontTools[lxml,ufo,unicode]>=3.32.0
Requires-Dist: fontMath>=0.4.8
Requires-Dist: defcon[pens]>=0.6.0
Requires-Dist: booleanOperations>=0.9.0
Dynamic: author
Dynamic: author-email
Dynamic: classifier
Dynamic: description
Dynamic: home-page
Dynamic: license
Dynamic: license-file
Dynamic: maintainer
Dynamic: maintainer-email
Dynamic: platform
Dynamic: requires-dist
Dynamic: requires-python
Dynamic: summary
